bismuthsdk/__about__.py
bismuthsdk/__init__.py
bismuthsdk/py.typed
bismuthsdk-0.3.8.dist-info/METADATA
bismuthsdk-0.3.8.dist-info/WHEEL
bismuthsdk-0.3.8.dist-info/licenses/LICENSE.txt
bismuthsdk-0.3.8.dist-info/RECORD
